crunchdao/__init__.py
crunchdao/api.py
crunchdao/utils.py
crunchdao-0.4.1.dist-info/METADATA
crunchdao-0.4.1.dist-info/WHEEL
crunchdao-0.4.1.dist-info/RECORD
