Metadata-Version: 2.1
Name: crunchdao
Version: 0.4.1
Summary: Python API for the Crunchdao machine learning tournament
License: MIT
Author: uuazed
Author-email: uuazed@gmail.com
Requires-Python: >=3.7.1,<4.0
Classifier: License :: OSI Approved :: MIT License
Classifier: Programming Language :: Python :: 3
Classifier: Programming Language :: Python :: 3.8
Classifier: Programming Language :: Python :: 3.9
Classifier: Programming Language :: Python :: 3.10
Classifier: Programming Language :: Python :: 3.11
Requires-Dist: holidays (>=0.23,<0.24)
Requires-Dist: inflection (>=0.5.1,<0.6.0)
Requires-Dist: pandas (>=1.3.5)
Requires-Dist: requests (>=2.27.0,<3.0.0)
Requires-Dist: tqdm (>=4.62.3,<5.0.0)
